README.md
setup.cfg
setup.py
mpb/__init__.py
mpb/mpb.py
mpb.egg-info/PKG-INFO
mpb.egg-info/SOURCES.txt
mpb.egg-info/dependency_links.txt
mpb.egg-info/top_level.txt